yet_another_figma_mcp/__init__.py
yet_another_figma_mcp/_version.py
yet_another_figma_mcp/server.py
yet_another_figma_mcp/cache/__init__.py
yet_another_figma_mcp/cache/index.py
yet_another_figma_mcp/cache/store.py
yet_another_figma_mcp/cli/__init__.py
yet_another_figma_mcp/cli/app.py
yet_another_figma_mcp/cli/cache.py
yet_another_figma_mcp/cli/i18n.py
yet_another_figma_mcp/cli/serve.py
yet_another_figma_mcp/cli/status.py
yet_another_figma_mcp/figma/__init__.py
yet_another_figma_mcp/figma/client.py
yet_another_figma_mcp/figma/exceptions.py
yet_another_figma_mcp/tools/__init__.py
yet_another_figma_mcp/tools/handlers.py
yet_another_figma_mcp/tools/simplify.py
yet_another_figma_mcp-0.2.0.dist-info/METADATA
yet_another_figma_mcp-0.2.0.dist-info/WHEEL
yet_another_figma_mcp-0.2.0.dist-info/entry_points.txt
yet_another_figma_mcp-0.2.0.dist-info/licenses/LICENSE
yet_another_figma_mcp-0.2.0.dist-info/RECORD
