Metadata-Version: 2.4
Name: yet-another-figma-mcp
Version: 0.2.0
Summary: Figma ファイルをローカルキャッシュし MCP サーバーとして提供する軽量ツール
Project-URL: Homepage, https://github.com/yk-lab/yet-another-figma-mcp
Project-URL: Repository, https://github.com/yk-lab/yet-another-figma-mcp
Project-URL: Issues, https://github.com/yk-lab/yet-another-figma-mcp/issues
Author: yk / k.yamada
License-Expression: MIT
License-File: LICENSE
Keywords: ai,cache,figma,mcp,model-context-protocol
Classifier: Development Status :: 3 - Alpha
Classifier: Intended Audience :: Developers
Classifier: License :: OSI Approved :: MIT License
Classifier: Programming Language :: Python :: 3
Classifier: Programming Language :: Python :: 3.13
Classifier: Topic :: Software Development :: Libraries :: Python Modules
Requires-Python: <3.14,>=3.13
Requires-Dist: httpx>=0.27.0
Requires-Dist: mcp[cli,rich]>=1.0.0
Requires-Dist: pydantic>=2.0.0
